DnsBench/__init__.py
DnsBench/__main__.py
DnsBench/check_dns.py
DnsBench/dns_ip.py
DnsBench/dns_provider.py
DnsBench/doh_tls.py
DnsBench/cache/dns_provider.json
DnsBench/cache/dns_resolved.json
DnsBench/cache/response.txt
DnsBench/web/index.html
DnsBench/web/css/all.min.css
DnsBench/web/css/animations.min.css
DnsBench/web/css/bootstrap.min.css
DnsBench/web/css/elementor-icons.min.css
DnsBench/web/css/flaticon.css
DnsBench/web/css/font-awesome.min.css
DnsBench/web/css/frontend-legacy.min.css
DnsBench/web/css/frontend.min.css
DnsBench/web/css/graphina-charts-for-elementor-public.css
DnsBench/web/css/intro-linker-public.css
DnsBench/web/css/ionicons.min.css
DnsBench/web/css/iqonic-extenstion.css
DnsBench/web/css/magnific-popup.css
DnsBench/web/css/marvy-custom-pro.css
DnsBench/web/css/marvy-custom.css
DnsBench/web/css/owl.carousel.min.css
DnsBench/web/css/post-4516.css
DnsBench/web/css/post-5.css
DnsBench/web/css/rs6.css
DnsBench/web/css/slick-theme.css
DnsBench/web/css/slick.css
DnsBench/web/css/style.min.css
DnsBench/web/css/styles.css
DnsBench/web/css/timeline.css
DnsBench/web/css/tox-progress.css
DnsBench/web/css/typicon.min.css
DnsBench/web/css/umetric-responsive.css
DnsBench/web/css/umetric-style.css
DnsBench/web/css/v4-shims.min.css
DnsBench/web/css/wow.css
DnsBench/web/images/loader.gif
DnsBench/web/images/logo.jpg
DnsBench/web/js/amcharts-animated.js
DnsBench/web/js/amcharts-core.js
DnsBench/web/js/amcharts-maps.js
DnsBench/web/js/amcharts-worldLow.js
DnsBench/web/js/apexcharts.min.js
DnsBench/web/js/appear.js
DnsBench/web/js/bootstrap.min.js
DnsBench/web/js/countdown.js
DnsBench/web/js/custom-map.js
DnsBench/web/js/dialog.min.js
DnsBench/web/js/dot-script.js
DnsBench/web/js/frontend-modules.min.js
DnsBench/web/js/frontend.min.js
DnsBench/web/js/graphina-charts-for-elementor-public.js
DnsBench/web/js/html5.js
DnsBench/web/js/intro-linker-public.js
DnsBench/web/js/iqonic-extenstion.js
DnsBench/web/js/isotope.pkgd.min.js
DnsBench-1.1.3.dist-info/LICENSE
DnsBench-1.1.3.dist-info/METADATA
DnsBench-1.1.3.dist-info/WHEEL
DnsBench-1.1.3.dist-info/entry_points.txt
DnsBench-1.1.3.dist-info/top_level.txt
DnsBench-1.1.3.dist-info/RECORD
