Metadata-Version: 2.1
Name: DnsBench
Version: 1.1.3
Summary: Multi-Threaded Python Application for Dns Benchmark
Home-page: https://github.com/aravindha1234u/dnsbench
Author: Aravindha Hariharan M, Kumaran S
Author-email: aravindha1234u@gmail.com, kumaransubramanian0007@gmail.com
License: MIT
Platform: UNKNOWN
Classifier: License :: OSI Approved :: MIT License
Classifier: Programming Language :: Python :: 3.9
Classifier: Operating System :: Microsoft :: Windows
Classifier: Operating System :: POSIX :: Linux
Requires-Python: >=3.5
Requires-Dist: Eel
Requires-Dist: pyinstaller
Requires-Dist: beautifulsoup4
Requires-Dist: requests
Requires-Dist: dnspython
Requires-Dist: dnspython[doh]
Requires-Dist: pyautogui
